da/__init__.py
da/__main__.py
da/api.py
da/common.py
da/freeze.py
da/pattern.py
da/sim.py
da/compiler/__init__.py
da/compiler/__main__.py
da/compiler/daast_dict.py
da/compiler/daast_nest.py
da/compiler/dast.py
da/compiler/incgen.py
da/compiler/parser.py
da/compiler/pseudo.py
da/compiler/pygen.py
da/compiler/symtab.py
da/compiler/ui.py
da/compiler/utils.py
da/examples/__init__.py
da/examples/2pcommit/__init__.py
da/examples/2pcommit/orig.da
da/examples/2pcommit/spec.da
da/examples/clpaxos/__init__.py
da/examples/clpaxos/spec.da
da/examples/crleader/__init__.py
da/examples/crleader/orig.da
da/examples/dscrash/__init__.py
da/examples/dscrash/orig.da
da/examples/dscrash/spec.da
da/examples/hsleader/__init__.py
da/examples/hsleader/orig.da
da/examples/hsleader/spec.da
da/examples/lamutex/__init__.py
da/examples/lamutex/orig.da
da/examples/lamutex/spec.da
da/examples/lamutex/spec_lam.da
da/examples/lapaxos/__init__.py
da/examples/lapaxos/orig.da
da/examples/pingpong/__init__.py
da/examples/pingpong/ping.da
da/examples/raft/__init__.py
da/examples/raft/orig.da
da/examples/ramutex/__init__.py
da/examples/ramutex/orig.da
da/examples/ramutex/spec.da
da/examples/ratoken/__init__.py
da/examples/ratoken/spec.da
da/examples/sktoken/__init__.py
da/examples/sktoken/orig.da
da/examples/vrpaxos/__init__.py
da/examples/vrpaxos/orig.da
da/importer/__init__.py
da/importer/py36.py
da/importer/py37.py
da/lib/__init__.py
da/tools/__init__.py
da/tools/unparse.py
da/transport/__init__.py
da/transport/base.py
da/transport/manager.py
da/transport/mesgloop.py
da/transport/sock.py
pyDistAlgo-1.1.0.dist-info/LICENSE
pyDistAlgo-1.1.0.dist-info/METADATA
pyDistAlgo-1.1.0.dist-info/WHEEL
pyDistAlgo-1.1.0.dist-info/top_level.txt
pyDistAlgo-1.1.0.dist-info/RECORD
