Metadata-Version: 2.1
Name: pyDistAlgo
Version: 1.1.0
Summary: A high-level language for distributed algorithms.
Home-page: https://github.com/DistAlgo/distalgo
Author: bolin
Author-email: bolin@cs.stonybrook.edu
License: UNKNOWN
Platform: UNKNOWN
Classifier: Development Status :: 4 - Beta
Classifier: Intended Audience :: Developers
Classifier: Programming Language :: Python :: 3
Classifier: Programming Language :: Python :: 3.5
Classifier: Programming Language :: Python :: 3.6
Classifier: Programming Language :: Python :: 3.7
Classifier: Topic :: Software Development :: Compilers
License-File: LICENSE
